{
  "name": "Size",
  "flags": {
    "sw5e-importer": {
      "timestamp": "2023-03-09T01:51:56.5562504+00:00",
      "importer_version": 3,
      "uid": "Feature.name-size.source-species.sourceName-ithorian"
    }
  },
  "type": "feat",
  "img": "modules/sw5e/icons/packs/Species/Ithorian.webp",
  "system": {
    "description": {
      "value": "<p>Shorter Ithorians stand around 6 feet while taller reach over 7 and a half. Regardless of your position in that range, your size is Medium.</p>",
      "chat": ""
    },
    "requirements": "Ithorian",
    "source": {
      "custom": "PHB",
      "revision": 1,
      "rules": "2024"
    },
    "type": {
      "value": "species",
      "subtype": ""
    },
    "uses": {
      "spent": 0,
      "recovery": []
    },
    "activities": {},
    "identifier": "size",
    "enchant": {},
    "prerequisites": {
      "level": null
    },
    "properties": []
  },
  "effects": [],
  "_id": "n7wazxlfPo956NmO",
  "folder": null,
  "sort": 0,
  "ownership": {
    "default": 0
  },
  "_stats": {
    "duplicateSource": null,
    "coreVersion": "12.331",
    "systemId": "dnd5e",
    "systemVersion": "3.3.1",
    "createdTime": 1730433988012,
    "modifiedTime": 1730433988012,
    "lastModifiedBy": "dnd5ebuilder0000"
  },
  "_key": "!items!n7wazxlfPo956NmO"
}
