{
  "name": "Heightened Reflexes",
  "flags": {
    "sw5e-importer": {
      "timestamp": "2023-03-09T01:52:12.7628531+00:00",
      "importer_version": 3,
      "uid": "Feature.name-heightened_reflexes.source-species.sourceName-nothoiin"
    },
    "dnd5e": {
      "migratedUses": null
    }
  },
  "type": "feat",
  "img": "modules/sw5e/icons/packs/Species/Nothoiin.webp",
  "system": {
    "description": {
      "value": "<p>Whenever you make a Dexterity ability check, attack roll, or saving throw, you can choose to add [[/r 1d4]] to the result. You can use this before or after the roll, but before the GM determines the roll's outcome. Once you've used this feature, you must complete a short or long rest before you can use it again.</p>",
      "chat": ""
    },
    "requirements": "Nothoiin",
    "source": {
      "custom": "EC",
      "revision": 1,
      "rules": "2024"
    },
    "type": {
      "value": "species",
      "subtype": ""
    },
    "uses": {
      "max": "1",
      "spent": 0,
      "recovery": []
    },
    "activities": {},
    "identifier": "heightened-reflexes",
    "enchant": {},
    "prerequisites": {
      "level": null
    },
    "properties": []
  },
  "effects": [],
  "_id": "NeK1mX7PnBqGbzBD",
  "folder": null,
  "sort": 0,
  "ownership": {
    "default": 0
  },
  "_stats": {
    "duplicateSource": null,
    "coreVersion": "12.331",
    "systemId": "dnd5e",
    "systemVersion": "3.3.1",
    "createdTime": 1730433988012,
    "modifiedTime": 1730434318223,
    "lastModifiedBy": "dnd5ebuilder0000"
  },
  "_key": "!items!NeK1mX7PnBqGbzBD"
}
