{
  "name": "One Big Baddie",
  "flags": {
    "sw5e-importer": {
      "timestamp": "2023-03-09T01:52:15.1794522+00:00",
      "importer_version": 3,
      "uid": "Feature.name-one_big_baddie.source-archetypeinvocation.sourceName-zoologist_pursuit"
    }
  },
  "type": "feat",
  "img": "modules/sw5e/icons/packs/Class%20Features/SCLR-Bonus.webp",
  "system": {
    "description": {
      "value": "<p><em><strong>Prerequisite:</strong> Size Medium or larger beast</em></p>\n<p>Your beast companion gains the following benefits:</p>\n<ul>\n<li>It deals double damage against structures.</li>\n<li>It can take the Guard action as a bonus action, but it can only guard you in this way.</li>\n<li>It can spend a bonus action to spend one of its Hit Dice to recover hit points.</li>\n<li>When it rolls a Hit Die to regain hit points, the minimum number of hit points it can regain from the roll equals twice its Constitution modifier (minimum of 2).</li></ul>",
      "chat": ""
    },
    "requirements": "Scholar (Zoologist Pursuit), Size Medium or larger beast",
    "source": {
      "custom": "EC",
      "revision": 1,
      "rules": "2024"
    },
    "type": {
      "value": "class",
      "subtype": "scholarInvocation"
    },
    "uses": {
      "spent": 0,
      "recovery": []
    },
    "activities": {},
    "identifier": "one-big-baddie",
    "enchant": {},
    "prerequisites": {
      "level": null
    },
    "properties": []
  },
  "effects": [],
  "_id": "3VgpQC7KQJpJETQz",
  "folder": null,
  "sort": 0,
  "ownership": {
    "default": 0
  },
  "_stats": {
    "duplicateSource": null,
    "coreVersion": "12.331",
    "systemId": "dnd5e",
    "systemVersion": "3.3.1",
    "createdTime": 1729983888725,
    "modifiedTime": 1729984342555,
    "lastModifiedBy": "dnd5ebuilder0000"
  },
  "_key": "!items!3VgpQC7KQJpJETQz"
}
