{
  "_id": "Tpq3FQTwrazsbPoW",
  "name": "Bulwark Technique",
  "type": "subclass",
  "img": "modules/sw5e/icons/packs/Archetypes/BulwarkTechnique.webp",
  "effects": [],
  "folder": null,
  "sort": 0,
  "flags": {
    "sw5e-importer": {
      "timestamp": "2023-03-09T01:51:58.3472117+00:00",
      "importer_version": 3,
      "uid": "Archetype.name-bulwark_technique"
    }
  },
  "system": {
    "description": {
      "value": "<h1>Bulwark Technique</h1>\n<p>Some scouts find themselves far from civilization not to hunt, gather intelligence, or escape danger, but to venture forth simply to defend those unable to defend themselves. Followers of the Bulwark Technique make use of advanced technology to contain those that threaten the undeserving.</p>",
      "chat": ""
    },
    "source": {
      "custom": "PHB"
    },
    "identifier": "bulwarktechnique",
    "classIdentifier": "scout",
    "advancement": [
      {
        "_id": "0ig0000000000000",
        "configuration": {
          "items": [
            {
              "uuid": "Compendium.sw5e.archetypefeatures.znaw7WWYo6g5JUoD",
              "optional": false
            },
            {
              "uuid": "Compendium.sw5e.archetypefeatures.9H0lc69pjr25CmUA",
              "optional": false
            },
            {
              "uuid": "Compendium.sw5e.archetypefeatures.3IRtRyM0ksFP8wdA",
              "optional": false
            }
          ],
          "optional": false,
          "spell": null
        },
        "level": 3,
        "title": "Features",
        "type": "ItemGrant",
        "value": {}
      },
      {
        "_id": "1ig0000000000000",
        "configuration": {
          "items": [
            {
              "uuid": "Compendium.sw5e.archetypefeatures.oWnJ0vssqOQZl6cC",
              "optional": false
            }
          ],
          "optional": false,
          "spell": null
        },
        "level": 7,
        "title": "Features",
        "type": "ItemGrant",
        "value": {}
      },
      {
        "_id": "2ig0000000000000",
        "configuration": {
          "items": [
            {
              "uuid": "Compendium.sw5e.archetypefeatures.558flgosIwSyAW9g",
              "optional": false
            }
          ],
          "optional": false,
          "spell": null
        },
        "level": 11,
        "title": "Features",
        "type": "ItemGrant",
        "value": {}
      },
      {
        "_id": "3ig0000000000000",
        "configuration": {
          "items": [
            {
              "uuid": "Compendium.sw5e.archetypefeatures.WvP6k5LuXOxqbn7o",
              "optional": false
            }
          ],
          "optional": false,
          "spell": null
        },
        "level": 15,
        "title": "Features",
        "type": "ItemGrant",
        "value": {}
      },
      {
        "_id": "4t00000000000000",
        "configuration": {
          "choices": [],
          "grants": [
            "armor:hvy"
          ],
          "mode": "default",
          "allowReplacements": false
        },
        "level": 3,
        "type": "Trait",
        "value": {
          "chosen": []
        }
      }
    ],
    "superiority": {
      "progression": 0
    },
    "spellcasting": {
      "superiorityProgression": "none"
    }
  },
  "ownership": {
    "default": 0
  },
  "_stats": {
    "systemId": "dnd5e",
    "systemVersion": "3.3.1",
    "coreVersion": "12.331",
    "createdTime": 1674493959749,
    "modifiedTime": 1732304669210,
    "lastModifiedBy": "dnd5ebuilder0000",
    "duplicateSource": null
  },
  "_key": "!items!Tpq3FQTwrazsbPoW"
}
