{
  "name": "Totem of the Vornskr",
  "flags": {
    "sw5e-importer": {
      "timestamp": "2023-03-09T01:52:15.1714563+00:00",
      "importer_version": 3,
      "uid": "Feature.name-totem_of_the_vornskr.source-archetypeinvocation.sourceName-totem_specialist"
    },
    "dnd5e": {
      "riders": {
        "activity": [],
        "effect": []
      }
    }
  },
  "type": "feat",
  "img": "modules/sw5e/icons/packs/Class%20Features/FGTR-Reaction.webp",
  "system": {
    "description": {
      "value": "<p>With this totem you are able to access the Force-enhanced senses of the vornskr, granting you advantage on Wisdom (Survival) checks, and you can't be surprised as long as you are not incapacitated.</p>\n<p>Additionally, you can invoke the totem as a bonus action to enter a state of hyper awareness for 1 minute or until you're incapacitated. Until the state ends, when you or another creature you can see within 60 feet of you makes an attack roll, a saving throw, or an ability check, you can use your reaction to cause the roll to have advantage or disadvantage. </p>",
      "chat": ""
    },
    "requirements": "Fighter (Totem Specialist)",
    "source": {
      "custom": "EC",
      "revision": 1,
      "rules": "2024"
    },
    "type": {
      "value": "class",
      "subtype": "fighterInvocation"
    },
    "uses": {
      "spent": 0,
      "recovery": []
    },
    "activities": {
      "sw5e0utility0000": {
        "_id": "sw5e0utility0000",
        "activation": {
          "type": "reaction"
        },
        "description": {},
        "duration": {
          "units": "minute",
          "value": "1"
        },
        "img": null,
        "range": {
          "units": "feet",
          "value": "60"
        },
        "roll": {},
        "target": {},
        "type": "utility"
      }
    },
    "identifier": "totem-of-the-vornskr",
    "enchant": {},
    "prerequisites": {
      "level": null
    },
    "properties": []
  },
  "effects": [],
  "_id": "dDAB3ltU9a5voAPo",
  "folder": null,
  "sort": 0,
  "ownership": {
    "default": 0
  },
  "_stats": {
    "duplicateSource": null,
    "coreVersion": "12.331",
    "systemId": "dnd5e",
    "systemVersion": "3.3.1",
    "createdTime": 1730433983637,
    "modifiedTime": 1733778272326,
    "lastModifiedBy": "dnd5ebuilder0000"
  },
  "_key": "!items!dDAB3ltU9a5voAPo"
}
