{
  "name": "Tactical Retreat",
  "flags": {
    "sw5e-importer": {
      "timestamp": "2023-03-09T01:51:58.3472117+00:00",
      "importer_version": 3,
      "uid": "Feature.name-tactical_retreat.source-archetypeinvocation.sourceName-tactician_pursuit"
    }
  },
  "type": "feat",
  "img": "modules/sw5e/icons/packs/Class%20Features/SCLR-Passive.webp",
  "system": {
    "description": {
      "value": "<p>When you take the Dash action, opportunity attacks made against you are made at disadvantage.</p>",
      "chat": ""
    },
    "requirements": "Scholar (Tactician Pursuit)",
    "source": {
      "custom": "PHB",
      "revision": 1,
      "rules": "2024"
    },
    "type": {
      "value": "class",
      "subtype": "scholarInvocation"
    },
    "uses": {
      "spent": 0,
      "recovery": []
    },
    "activities": {},
    "identifier": "tactical-retreat",
    "enchant": {},
    "prerequisites": {
      "level": null
    },
    "properties": []
  },
  "effects": [],
  "_id": "O2c7VXUCeJPX2wZI",
  "folder": null,
  "sort": 0,
  "ownership": {
    "default": 0
  },
  "_stats": {
    "duplicateSource": null,
    "coreVersion": "12.331",
    "systemId": "dnd5e",
    "systemVersion": "3.3.1",
    "createdTime": 1729983888725,
    "modifiedTime": 1729983888725,
    "lastModifiedBy": "dnd5ebuilder0000"
  },
  "_key": "!items!O2c7VXUCeJPX2wZI"
}
