{
  "name": "Pa'lowick",
  "flags": {
    "sw5e-importer": {
      "timestamp": "2023-03-09T01:52:12.2881282+00:00",
      "importer_version": 3,
      "uid": "Species.name-palowick"
    }
  },
  "type": "race",
  "img": "modules/sw5e-module-test/icons/packs/Species/PaLowick.webp",
  "system": {
    "description": {
      "value": "<h2>Biology and Appearance</h2>\n<p>The pa'lowick are a species of humanoid amphibians who live in the coastal salt marshes of Lowick. They have compact but rotund midsections that top a pair of long, spindly legs ending in anisodactylic feet—three toes pointing forward, one back. This configuration, combined with their powerful lungs, enabled them to swim.</p>\n<p>The most prominent feature of pa'lowick physiology is their prehensile snout, which ends in a pair of pouty, human-like lips. Pa'lowick are also born with sharp tusks, which some lose by middle age.</p>\n<h2>Society and Culture</h2>\n<p>Pa'lowick live in large, independent communities with a feudal system of government. Many pa'lowick become fishers or hunters, as their biology allows. </p>\n<p>Songs and stories are the most treasured aspect of pa'lowick culture. Pa'lowick music runs the gamut of genres and subjects, although religious music is particularly common. Cultural heritage, such as history, genealogy, and parables, is largely passed down orally. Every Pa'lowick community has a dedicated storyteller; the esteem afforded this individual makes the position a coveted one. Large lungs make the Pa'lowick hearty singers and affords at least some members of the species the ability to scream loudly and disarm opponents in combat.</p>\n<h2>Names</h2>\n<p>Pa'lowick names tend to grow longer as the family tree grows older, with each generation adding a few syllables they are fond of.</p>\n<p><strong>Male Names.</strong> Loran, Jelanto, Neeamesh, Samoos</p>\n<p><strong>Female Names.</strong> Larisselle, Rensilla, Sy, Tripika</p>\n<p><strong>Surnames.</strong> Chatrunis, Dym, Geeci, Snootles</p>",
      "chat": ""
    },
    "source": {
      "custom": "EC"
    },
    "identifier": "palowick",
    "details": {
      "isDroid": false
    },
    "type": {
      "value": "humanoid"
    },
    "movement": {
      "walk": 30,
      "swim": 30,
      "burrow": null,
      "climb": null,
      "fly": null,
      "units": null,
      "hover": false
    },
    "senses": {
      "darkvision": null,
      "blindsight": null,
      "tremorsense": null,
      "truesight": null,
      "units": null,
      "special": ""
    },
    "advancement": [
      {
        "_id": "19U7BdhFhNHg11dy",
        "type": "ItemGrant",
        "configuration": {
          "items": [
            {
              "uuid": "Compendium.sw5e-module-test.speciesfeatures.pTabPCEgnRVk4pF1",
              "optional": false
            },
            {
              "uuid": "Compendium.sw5e-module-test.speciesfeatures.GUlw2qoRPsM8SB9s",
              "optional": false
            },
            {
              "uuid": "Compendium.sw5e-module-test.speciesfeatures.O35Gg4ria1KqD0rV",
              "optional": false
            },
            {
              "uuid": "Compendium.sw5e-module-test.speciesfeatures.6hIe0SS67ihWL4F7",
              "optional": false
            },
            {
              "uuid": "Compendium.sw5e-module-test.speciesfeatures.XICRjYFLfwBxa8XJ",
              "optional": false
            },
            {
              "uuid": "Compendium.sw5e-module-test.speciesfeatures.nPNrvGe9bY9gP0RH",
              "optional": false
            },
            {
              "uuid": "Compendium.sw5e-module-test.speciesfeatures.kgxmQdNHoHQkwxAk",
              "optional": false
            },
            {
              "uuid": "Compendium.sw5e-module-test.speciesfeatures.zoeMKHP8qDVHT090",
              "optional": false
            },
            {
              "uuid": "Compendium.sw5e-module-test.speciesfeatures.9JGXFvGbp13FCEe5",
              "optional": false
            },
            {
              "uuid": "Compendium.sw5e-module-test.speciesfeatures.9URRUqO7RSlzJ7UH",
              "optional": false
            },
            {
              "uuid": "Compendium.sw5e-module-test.speciesfeatures.1ODDUIlUUXoU9EQ3",
              "optional": false
            }
          ],
          "optional": true,
          "spell": null
        },
        "value": {},
        "level": 0,
        "title": "Features"
      },
      {
        "_id": "ZHdK6pDO8zh1s6uT",
        "type": "AbilityScoreImprovement",
        "configuration": {
          "fixed": {
            "dex": 2,
            "cha": 1
          },
          "points": 0,
          "cap": 2
        },
        "value": {
          "type": "asi"
        },
        "level": 0
      },
      {
        "_id": "8y4JnCRZYOm1aNyG",
        "type": "Size",
        "configuration": {
          "sizes": [
            "med"
          ]
        },
        "value": {},
        "level": 0
      }
    ],
    "skinColorOptions": {
      "value": "Generally tan and greenish hues"
    },
    "hairColorOptions": {
      "value": "None"
    },
    "eyeColorOptions": {
      "value": "Green, blue, gray, red-orange"
    },
    "colorScheme": {
      "value": ""
    },
    "distinctions": {
      "value": "Long snout, bulbous body on thin legs"
    },
    "heightAverage": {
      "value": "4'6\""
    },
    "heightRollMod": {
      "value": "+2d6\""
    },
    "weightAverage": {
      "value": "65 lbs."
    },
    "weightRollMod": {
      "value": "x(2d4) lb."
    },
    "homeworld": {
      "value": "Lowick"
    },
    "slanguage": {
      "value": "Lowickese"
    },
    "droidDistinctions": {
      "value": ""
    },
    "manufacturer": {
      "value": ""
    },
    "droidLanguage": {
      "value": ""
    }
  },
  "effects": [
    {
      "_id": "DOEcD2uiPDNcMRRg",
      "changes": [],
      "disabled": false,
      "duration": {
        "startTime": null,
        "seconds": null,
        "combat": null,
        "rounds": null,
        "turns": null,
        "startRound": null,
        "startTurn": null
      },
      "tint": "#ffffff",
      "transfer": true,
      "flags": {},
      "origin": null,
      "name": "Pa'lowick",
      "description": "",
      "statuses": [],
      "_stats": {
        "coreVersion": "12.330",
        "systemId": null,
        "systemVersion": null,
        "createdTime": null,
        "modifiedTime": null,
        "lastModifiedBy": null,
        "compendiumSource": null,
        "duplicateSource": null
      },
      "img": "modules/sw5e-module-test/icons/packs/Species/Pa%27lowick.webp",
      "type": "base",
      "system": {},
      "sort": 0,
      "_key": "!items.effects!D55bkJs8yy53ZCOk.DOEcD2uiPDNcMRRg"
    }
  ],
  "_id": "D55bkJs8yy53ZCOk",
  "folder": null,
  "sort": 0,
  "ownership": {
    "default": 0
  },
  "_stats": {
    "systemId": "dnd5e",
    "systemVersion": "3.3.1",
    "coreVersion": "12.330",
    "createdTime": 1720296028336,
    "modifiedTime": 1723579432614,
    "lastModifiedBy": "dnd5ebuilder0000",
    "duplicateSource": null
  },
  "_key": "!items!D55bkJs8yy53ZCOk"
}
