{
  "name": "Improved Power",
  "flags": {
    "sw5e-importer": {
      "timestamp": "2023-03-09T01:51:57.62763+00:00",
      "importer_version": 3,
      "uid": "Feature.name-improved_power.source-classinvocation.sourceName-consular"
    }
  },
  "type": "feat",
  "img": "modules/sw5e/icons/packs/Class%20Features/CSLR-Passive.webp",
  "system": {
    "description": {
      "value": "<p>When you roll damage for a power, you can spend 1 additional force point to reroll a number of the damage dice up to your Wisdom or Charisma modifier (your choice, minimum of one). You must use the new rolls.</p>\n<p>You can use Improved Power even if you have already used a different Force-Empowered Casting option during the casting of the power.</p>",
      "chat": ""
    },
    "requirements": "Consular",
    "source": {
      "custom": "PHB",
      "revision": 1,
      "rules": "2024"
    },
    "type": {
      "value": "class",
      "subtype": "consularInvocation"
    },
    "uses": {
      "spent": 0,
      "recovery": []
    },
    "activities": {},
    "identifier": "improved-power",
    "enchant": {},
    "prerequisites": {
      "level": null
    },
    "properties": []
  },
  "effects": [],
  "_id": "nGmG9wAeHQBX2Pqi",
  "folder": null,
  "sort": 0,
  "ownership": {
    "default": 0
  },
  "_stats": {
    "duplicateSource": null,
    "coreVersion": "12.331",
    "systemId": "dnd5e",
    "systemVersion": "3.3.1",
    "createdTime": 1729983888725,
    "modifiedTime": 1729983888725,
    "lastModifiedBy": "dnd5ebuilder0000"
  },
  "_key": "!items!nGmG9wAeHQBX2Pqi"
}
